telebot_wizard/__init__.py
telebot_wizard/cli.py
telebot_wizard/exceptions.py
telebot_wizard/wizard.py
telebot_wizard-1.0.1.dist-info/licenses/LICENSE
telebot_wizard-1.0.1.dist-info/METADATA
telebot_wizard-1.0.1.dist-info/WHEEL
telebot_wizard-1.0.1.dist-info/entry_points.txt
telebot_wizard-1.0.1.dist-info/top_level.txt
telebot_wizard-1.0.1.dist-info/RECORD
