Metadata-Version: 2.4
Name: telebot-wizard
Version: 1.0.1
Summary: Zero-Code Telegram Bot Builder for TeleBot
Home-page: https://t.em/UzMaxBoy
Author: Yoqubov Javohir
Author-email: Yoqubov javohir <rakuzenuz@gmail.com>
License: MIT
Project-URL: Homepage, https://t.me/UzMaxBoy
Project-URL: Bug Tracker, https://t.me/UzMaxBoy
Project-URL: Documentation, https://t.me/UzMaxBoy
Project-URL: Source Code, https://t.me/UzMaxBoy
Keywords: telegram,bot,telebot,zero-code,builder
Platform: any
Classifier: Development Status :: 5 - Production/Stable
Classifier: Intended Audience :: Developers
Classifier: License :: OSI Approved :: MIT License
Classifier: Operating System :: OS Independent
Classifier: Programming Language :: Python :: 3
Classifier: Programming Language :: Python :: 3.8
Classifier: Programming Language :: Python :: 3.9
Classifier: Programming Language :: Python :: 3.10
Classifier: Programming Language :: Python :: 3.11
Classifier: Programming Language :: Python :: 3.12
Classifier: Topic :: Software Development :: Libraries :: Python Modules
Classifier: Topic :: Communications :: Chat
Classifier: Topic :: Communications :: Internet Phone
Classifier: Operating System :: OS Independent
Requires-Python: >=3.8
License-File: LICENSE
Requires-Dist: pyTelegramBotAPI>=4.0.0
Provides-Extra: dev
Requires-Dist: pytest>=6.0.0; extra == "dev"
Requires-Dist: pytest-cov>=2.0.0; extra == "dev"
Requires-Dist: black>=21.0.0; extra == "dev"
Requires-Dist: flake8>=3.9.0; extra == "dev"
Requires-Dist: mypy>=0.910; extra == "dev"
Provides-Extra: docs
Requires-Dist: sphinx>=4.0.0; extra == "docs"
Requires-Dist: sphinx-rtd-theme>=1.0.0; extra == "docs"
Dynamic: author
Dynamic: home-page
Dynamic: license-file
Dynamic: platform
Dynamic: requires-python
